opensesame_extensions/updater/__init__.py
opensesame_extensions/updater/updater/__init__.py
opensesame_extensions/updater/updater/locale/ar.qm
opensesame_extensions/updater/updater/locale/ar.ts
opensesame_extensions/updater/updater/locale/bn.qm
opensesame_extensions/updater/updater/locale/bn.ts
opensesame_extensions/updater/updater/locale/de.qm
opensesame_extensions/updater/updater/locale/de.ts
opensesame_extensions/updater/updater/locale/es.qm
opensesame_extensions/updater/updater/locale/es.ts
opensesame_extensions/updater/updater/locale/fr.qm
opensesame_extensions/updater/updater/locale/fr.ts
opensesame_extensions/updater/updater/locale/he.qm
opensesame_extensions/updater/updater/locale/he.ts
opensesame_extensions/updater/updater/locale/hi.qm
opensesame_extensions/updater/updater/locale/hi.ts
opensesame_extensions/updater/updater/locale/id.qm
opensesame_extensions/updater/updater/locale/id.ts
opensesame_extensions/updater/updater/locale/it.qm
opensesame_extensions/updater/updater/locale/it.ts
opensesame_extensions/updater/updater/locale/ja.qm
opensesame_extensions/updater/updater/locale/ja.ts
opensesame_extensions/updater/updater/locale/ko.qm
opensesame_extensions/updater/updater/locale/ko.ts
opensesame_extensions/updater/updater/locale/nl.qm
opensesame_extensions/updater/updater/locale/nl.ts
opensesame_extensions/updater/updater/locale/pt.qm
opensesame_extensions/updater/updater/locale/pt.ts
opensesame_extensions/updater/updater/locale/ru.qm
opensesame_extensions/updater/updater/locale/ru.ts
opensesame_extensions/updater/updater/locale/tr.qm
opensesame_extensions/updater/updater/locale/tr.ts
opensesame_extensions/updater/updater/locale/translatables.ts
opensesame_extensions/updater/updater/locale/yue.qm
opensesame_extensions/updater/updater/locale/yue.ts
opensesame_extensions/updater/updater/locale/zh.qm
opensesame_extensions/updater/updater/locale/zh.ts
opensesame_extensions/updater/updater/update_widget.py
opensesame_extensions/updater/updater/update_widget.ui
opensesame_extension_updater-0.2.2.dist-info/METADATA
opensesame_extension_updater-0.2.2.dist-info/WHEEL
opensesame_extension_updater-0.2.2.dist-info/licenses/COPYING
opensesame_extension_updater-0.2.2.dist-info/RECORD
