Metadata-Version: 2.4
Name: opensesame-extension-updater
Version: 0.2.2
Summary: Checks for updates to extensions and plugins in OpenSesame
License: COPYING
License-File: COPYING
Author: Sebastiaan Mathôt
Author-email: s.mathot@cogsci.nl
Requires-Python: >=3.7
Classifier: License :: Other/Proprietary License
Classifier: Programming Language :: Python :: 3
Classifier: Programming Language :: Python :: 3.7
Classifier: Programming Language :: Python :: 3.8
Classifier: Programming Language :: Python :: 3.9
Classifier: Programming Language :: Python :: 3.10
Classifier: Programming Language :: Python :: 3.11
Classifier: Programming Language :: Python :: 3.12
Classifier: Programming Language :: Python :: 3.13
Classifier: Programming Language :: Python :: 3.14
Requires-Dist: opensesame-core (>=4.1.0a0)
Project-URL: Homepage, https://osdoc.cogsci.nl
Project-URL: Repository, https://github.com/open-cogsci/opensesame-extension-updater
